old_code/__init__.py
old_code/parsing_steps/__init__.py
old_code/parsing_steps/base_parsing_step.py
old_code/parsing_steps/base_parsing_step_old.py
old_code/parsing_steps/mixins.py
old_code/parsing_steps/parsing_step.py
parsing_steps/__init__.py
parsing_steps/base.py
parsing_steps/base_async.py
parsing_steps/simple.py
parsing_steps/simple_async.py
parsing_steps-0.0.5.dist-info/LICENSE
parsing_steps-0.0.5.dist-info/METADATA
parsing_steps-0.0.5.dist-info/WHEEL
parsing_steps-0.0.5.dist-info/top_level.txt
parsing_steps-0.0.5.dist-info/RECORD
